{
  "updated_at": "2026-06-26T00:10:00+08:00",
  "site": "https://gh.reelos.ai",
  "reports": [
    {
      "type": "weekly",
      "period": "2026-06-25",
      "title": "GitHub 热榜情报周报 · 2026-06-25",
      "html": "/weekly/2026-06-25/",
      "markdown": "/github-trending-weekly-20260625.md",
      "top10": "/top10-2026-06-25.json",
      "raw_data": "/trending-data-2026-06-25.json",
      "top_count": 10,
      "candidate_count": 60,
      "readme_coverage": 59,
      "api_failures": 0
    }
  ]
}
