[
  {
    "name": "diegosouzapw/OmniRoute",
    "rank": 1,
    "stars_total": 16610,
    "stars_today_or_period": 4506,
    "language": "TypeScript",
    "source_dimension": "all,typescript"
  },
  {
    "name": "ogulcancelik/herdr",
    "rank": 2,
    "stars_total": 16016,
    "stars_today_or_period": 3928,
    "language": "Rust",
    "source_dimension": "all,rust"
  },
  {
    "name": "jamiepine/voicebox",
    "rank": 3,
    "stars_total": 40982,
    "stars_today_or_period": 2945,
    "language": "TypeScript",
    "source_dimension": "typescript"
  },
  {
    "name": "wonderwhy-er/DesktopCommanderMCP",
    "rank": 4,
    "stars_total": 8150,
    "stars_today_or_period": 1678,
    "language": "TypeScript",
    "source_dimension": "all,typescript"
  },
  {
    "name": "ChromeDevTools/chrome-devtools-mcp",
    "rank": 5,
    "stars_total": 46837,
    "stars_today_or_period": 872,
    "language": "TypeScript",
    "source_dimension": "typescript"
  },
  {
    "name": "facebook/astryx",
    "rank": 6,
    "stars_total": 8519,
    "stars_today_or_period": 2397,
    "language": "TypeScript",
    "source_dimension": "all,typescript"
  },
  {
    "name": "oven-sh/bun",
    "rank": 7,
    "stars_total": 94654,
    "stars_today_or_period": 1190,
    "language": "Rust",
    "source_dimension": "rust"
  },
  {
    "name": "langflow-ai/langflow",
    "rank": 8,
    "stars_total": 151811,
    "stars_today_or_period": 647,
    "language": "Python",
    "source_dimension": "python"
  },
  {
    "name": "ruvnet/RuView",
    "rank": 9,
    "stars_total": 80391,
    "stars_today_or_period": 3763,
    "language": "Rust",
    "source_dimension": "all,rust"
  },
  {
    "name": "alibaba/page-agent",
    "rank": 10,
    "stars_total": 26374,
    "stars_today_or_period": 2666,
    "language": "TypeScript",
    "source_dimension": "all,typescript"
  }
]